getfilelistpy/__init__.py
getfilelistpy/getfilelist.py
tests/__init__.py
tests/test_getfilelist.py
getfilelistpy-1.0.7.dist-info/LICENCE
getfilelistpy-1.0.7.dist-info/METADATA
getfilelistpy-1.0.7.dist-info/WHEEL
getfilelistpy-1.0.7.dist-info/top_level.txt
getfilelistpy-1.0.7.dist-info/RECORD
